texture2ddecoder_rs-0.1.0.dist-info/METADATA
texture2ddecoder_rs-0.1.0.dist-info/WHEEL
texture2ddecoder_rs.libs/libgcc_s-60abea67.so.1
texture2ddecoder_rs/__init__.py
texture2ddecoder_rs/__init__.pyi
texture2ddecoder_rs/py.typed
texture2ddecoder_rs/texture2ddecoder_rs.cpython-310-aarch64-linux-gnu.so
texture2ddecoder_rs-0.1.0.dist-info/RECORD
