Metadata-Version: 2.3
Name: texture2ddecoder_rs
Version: 0.1.0
Summary: texture2ddecoder python bindings
Home-Page: https://crates.io/crates/texture2ddecoder
Author: Rudolf Kolbe <rkolbe96@gmail.com>
Author-email: Rudolf Kolbe <rkolbe96@gmail.com>
License: MIT OR Apache-2.0
Project-URL: Source Code, https://github.com/UniversalGameExtraction/texture2ddecoder
